dxface/__init__.py
dxface/arc.py
dxface/circle.py
dxface/entities.py
dxface/line.py
dxface/lwpolyline.py
dxface/polyline.py
dxface-0.0.6.dist-info/LICENSE
dxface-0.0.6.dist-info/METADATA
dxface-0.0.6.dist-info/WHEEL
dxface-0.0.6.dist-info/top_level.txt
dxface-0.0.6.dist-info/RECORD
